flownat/__init__.py
flownat/core.py
flownat/plot.py
flownat/modules/catch_del_all.py
flownat/modules/flow_estimates.py
flownat/modules/naturalisation.py
flownat/modules/upstream_takes.py
flownat/modules/usage_estimates.py
nz_flow_naturalisation-0.2.2.dist-info/METADATA
nz_flow_naturalisation-0.2.2.dist-info/WHEEL
nz_flow_naturalisation-0.2.2.dist-info/licenses/LICENSE
nz_flow_naturalisation-0.2.2.dist-info/RECORD
